jod/__init__.py
jod/run_async.py
jod-0.0.1.dist-info/METADATA
jod-0.0.1.dist-info/WHEEL
jod-0.0.1.dist-info/top_level.txt
jod-0.0.1.dist-info/RECORD
