Metadata-Version: 2.1
Name: jod
Version: 0.0.1
Summary: Join, or Die simple asynchronous execution
Home-page: https://gitlab.com/musingsole/jod
Author: musingsole
Author-email: musingsole@gmail.com
License: UNKNOWN
Platform: UNKNOWN
Classifier: Programming Language :: Python :: 3
Classifier: License :: OSI Approved :: MIT License
Classifier: Operating System :: OS Independent
